Workbook

Sheet Dashboard
A1: STORE INVENTORY & SALES PERFORMANCE DASHBOARD
A4: =HYPERLINK("#'Dashboard'!A1", "📊 Dashboard") -> 📊 Dashboard | D4: =HYPERLINK("#'Product Master'!A1", "📦 Product Master") -> 📦 Product Master | H4: =HYPERLINK("#'Purchase Entry'!A1", "📥 Purchase Entry") -> 📥 Purchase Entry | L4: =HYPERLINK("#'Sales Entry'!A1", "📤 Sales Entry") -> 📤 Sales Entry | O4: =HYPERLINK("#'Supplier Management'!A1", "🤝 Suppliers") -> 🤝 Suppliers | R4: =HYPERLINK("#'Reports'!A1", "📈 Reports") -> 📈 Reports
A6: TOTAL PRODUCTS REGISTRIES | E6: TOTAL INVENTORY VALUATION | I6: LOW STOCK ALERTS | M6: OUT OF STOCK ITEMS | Q6: MONTHLY TOTAL REVENUE
A7: =COUNTA(ProductMaster[Product ID]) -> 50 | E7: =SUM(ProductMaster[Stock Value]) -> 36745.5 | I7: =COUNTIF(ProductMaster[Status], "Low Stock") -> 8 | M7: =COUNTIF(ProductMaster[Status], "Out of Stock") -> 1 | Q7: =SUM(SalesEntry[Total Amount]) -> 18715.15
X10: Category | Y10: Stock Value | AA10: Month | AB10: Sales Value
X11: Electronics | Y11: =SUMIF(ProductMaster[Category], X11, ProductMaster[Stock Value]) -> 21485 | AA11: Jan | AB11: =SUMIFS(SalesEntry[Total Amount], SalesEntry[Date], ">=2026-01-01", SalesEntry[Date], "<=2026-01-31") -> 2930
X12: Apparel | Y12: =SUMIF(ProductMaster[Category], X12, ProductMaster[Stock Value]) -> 7424 | AA12: Feb | AB12: =SUMIFS(SalesEntry[Total Amount], SalesEntry[Date], ">=2026-02-01", SalesEntry[Date], "<=2026-02-28") -> 2547.97
X13: Grocery | Y13: =SUMIF(ProductMaster[Category], X13, ProductMaster[Stock Value]) -> 1613 | AA13: Mar | AB13: =SUMIFS(SalesEntry[Total Amount], SalesEntry[Date], ">=2026-03-01", SalesEntry[Date], "<=2026-03-31") -> 2098.06
X14: Pharmacy | Y14: =SUMIF(ProductMaster[Category], X14, ProductMaster[Stock Value]) -> 2542.5 | AA14: Apr | AB14: =SUMIFS(SalesEntry[Total Amount], SalesEntry[Date], ">=2026-04-01", SalesEntry[Date], "<=2026-04-30") -> 4945.92
X15: Home & Kitchen | Y15: =SUMIF(ProductMaster[Category], X15, ProductMaster[Stock Value]) -> 3681 | AA15: May | AB15: =SUMIFS(SalesEntry[Total Amount], SalesEntry[Date], ">=2026-05-01", SalesEntry[Date], "<=2026-05-31") -> 6193.2
A21: CRITICAL LOW STOCK ALERTS | I21: TOP 5 SELLING PRODUCTS

Sheet Reports
A1: AUTOMATED REPORTS SUMMARY
A4: =HYPERLINK("#'Dashboard'!A1", "📊 Dashboard") -> 📊 Dashboard | D4: =HYPERLINK("#'Product Master'!A1", "📦 Product Master") -> 📦 Product Master | H4: =HYPERLINK("#'Purchase Entry'!A1", "📥 Purchase Entry") -> 📥 Purchase Entry | L4: =HYPERLINK("#'Sales Entry'!A1", "📤 Sales Entry") -> 📤 Sales Entry | O4: =HYPERLINK("#'Supplier Management'!A1", "🤝 Suppliers") -> 🤝 Suppliers | R4: =HYPERLINK("#'Reports'!A1", "📈 Reports") -> 📈 Reports
A6: COST OF GOODS SOLD (COGS) | F6: AVERAGE INVENTORY VALUE | K6: INVENTORY TURNOVER RATIO | P6: DAYS SALES OF INVENTORY (DSI)
A7: =SUMPRODUCT(SalesEntry[Quantity Sold], SUMIF(ProductMaster[Product ID], SalesEntry[Product ID], ProductMaster[Cost Price])) -> 12854 | F7: =(SUMPRODUCT(ProductMaster[Initial Stock], ProductMaster[Cost Price]) + SUM(ProductMaster[Stock Value])) / 2 -> 33071.25 | K7: =IF(F7>0, A7/F7, 0) -> 0.38867596 | P7: =IF(K7>0, 365/K7, 0) -> 939.0856
A10: CRITICAL LOW STOCK REPORT (Dynamic FILTER) | I10: DEAD STOCK REPORT (Auto-updating)
A11: Product ID | B11: Product Name | C11: Category | D11: Current Stock | E11: Reorder Level | F11: Status | I11: Product ID | J11: Product Name | K11: Category | L11: Current Stock | M11: Reorder Level
A12: =IFERROR(INDEX('Product Master'!$A$7:$A$1000,_xlfn.AGGREGATE(15,6,(ROW('Product Master'!$A$7:$A$1000)-ROW('Product Master'!$A$7)+1)/(('Product Master'!$A$7:$A$1000<>"")*('Product Master'!$P$7:$P$1000="Low Stock")),ROWS($A$12:A12))),"") -> PRD-00003 | B12: =IF($A12="","",INDEX('Product Master'!$B$7:$B$1000,MATCH($A12,'Product Master'!$A$7:$A$1000,0))) -> Apple iPad Air (64GB) | C12: =IF($A12="","",INDEX('Product Master'!$C$7:$C$1000,MATCH($A12,'Product Master'!$A$7:$A$1000,0))) -> Electronics | D12: =IF($A12="","",INDEX('Product Master'!$M$7:$M$1000,MATCH($A12,'Product Master'!$A$7:$A$1000,0))) -> 17 | E12: =IF($A12="","",INDEX('Product Master'!$N$7:$N$1000,MATCH($A12,'Product Master'!$A$7:$A$1000,0))) -> 20 | F12: =IF($A12="","",INDEX('Product Master'!$P$7:$P$1000,MATCH($A12,'Product Master'!$A$7:$A$1000,0))) -> Low Stock | I12: =IFERROR(INDEX('Product Master'!$A$7:$A$1000,_xlfn.AGGREGATE(15,6,(ROW('Product Master'!$A$7:$A$1000)-ROW('Product Master'!$A$7)+1)/(('Product Master'!$A$7:$A$1000<>"")*('Product Master'!$P$7:$P$1000="Out of Stock")),ROWS($I$12:I12))),"") -> PRD-00041 | J12: =IF($I12="","",INDEX('Product Master'!$B$7:$B$1000,MATCH($I12,'Product Master'!$A$7:$A$1000,0))) -> Dyson V11 Cordless Vacuum | K12: =IF($I12="","",INDEX('Product Master'!$C$7:$C$1000,MATCH($I12,'Product Master'!$A$7:$A$1000,0))) -> Home & Kitchen | L12: =IF($I12="","",INDEX('Product Master'!$M$7:$M$1000,MATCH($I12,'Product Master'!$A$7:$A$1000,0))) -> 0 | M12: =IF($I12="","",INDEX('Product Master'!$N$7:$N$1000,MATCH($I12,'Product Master'!$A$7:$A$1000,0))) -> 2
A13: =IFERROR(INDEX('Product Master'!$A$7:$A$1000,_xlfn.AGGREGATE(15,6,(ROW('Product Master'!$A$7:$A$1000)-ROW('Product Master'!$A$7)+1)/(('Product Master'!$A$7:$A$1000<>"")*('Product Master'!$P$7:$P$1000="Low Stock")),ROWS($A$12:A13))),"") -> PRD-00005 | B13: =IF($A13="","",INDEX('Product Master'!$B$7:$B$1000,MATCH($A13,'Product Master'!$A$7:$A$1000,0))) -> Logitech C920 HD Pro Webcam | C13: =IF($A13="","",INDEX('Product Master'!$C$7:$C$1000,MATCH($A13,'Product Master'!$A$7:$A$1000,0))) -> Electronics | D13: =IF($A13="","",INDEX('Product Master'!$M$7:$M$1000,MATCH($A13,'Product Master'!$A$7:$A$1000,0))) -> 12 | E13: =IF($A13="","",INDEX('Product Master'!$N$7:$N$1000,MATCH($A13,'Product Master'!$A$7:$A$1000,0))) -> 20 | F13: =IF($A13="","",INDEX('Product Master'!$P$7:$P$1000,MATCH($A13,'Product Master'!$A$7:$A$1000,0))) -> Low Stock | I13: =IFERROR(INDEX('Product Master'!$A$7:$A$1000,_xlfn.AGGREGATE(15,6,(ROW('Product Master'!$A$7:$A$1000)-ROW('Product Master'!$A$7)+1)/(('Product Master'!$A$7:$A$1000<>"")*('Product Master'!$P$7:$P$1000="Out of Stock")),ROWS($I$12:I13))),"") | J13: =IF($I13="","",INDEX('Product Master'!$B$7:$B$1000,MATCH($I13,'Product Master'!$A$7:$A$1000,0))) | K13: =IF($I13="","",INDEX('Product Master'!$C$7:$C$1000,MATCH($I13,'Product Master'!$A$7:$A$1000,0))) | L13: =IF($I13="","",INDEX('Product Master'!$M$7:$M$1000,MATCH($I13,'Product Master'!$A$7:$A$1000,0))) | M13: =IF($I13="","",INDEX('Product Master'!$N$7:$N$1000,MATCH($I13,'Product Master'!$A$7:$A$1000,0)))
A14: =IFERROR(INDEX('Product Master'!$A$7:$A$1000,_xlfn.AGGREGATE(15,6,(ROW('Product Master'!$A$7:$A$1000)-ROW('Product Master'!$A$7)+1)/(('Product Master'!$A$7:$A$1000<>"")*('Product Master'!$P$7:$P$1000="Low Stock")),ROWS($A$12:A14))),"") -> PRD-00007 | B14: =IF($A14="","",INDEX('Product Master'!$B$7:$B$1000,MATCH($A14,'Product Master'!$A$7:$A$1000,0))) -> Anker PowerCore 26800mAh | C14: =IF($A14="","",INDEX('Product Master'!$C$7:$C$1000,MATCH($A14,'Product Master'!$A$7:$A$1000,0))) -> Electronics | D14: =IF($A14="","",INDEX('Product Master'!$M$7:$M$1000,MATCH($A14,'Product Master'!$A$7:$A$1000,0))) -> 18 | E14: =IF($A14="","",INDEX('Product Master'!$N$7:$N$1000,MATCH($A14,'Product Master'!$A$7:$A$1000,0))) -> 20 | F14: =IF($A14="","",INDEX('Product Master'!$P$7:$P$1000,MATCH($A14,'Product Master'!$A$7:$A$1000,0))) -> Low Stock | I14: =IFERROR(INDEX('Product Master'!$A$7:$A$1000,_xlfn.AGGREGATE(15,6,(ROW('Product Master'!$A$7:$A$1000)-ROW('Product Master'!$A$7)+1)/(('Product Master'!$A$7:$A$1000<>"")*('Product Master'!$P$7:$P$1000="Out of Stock")),ROWS($I$12:I14))),"") | J14: =IF($I14="","",INDEX('Product Master'!$B$7:$B$1000,MATCH($I14,'Product Master'!$A$7:$A$1000,0))) | K14: =IF($I14="","",INDEX('Product Master'!$C$7:$C$1000,MATCH($I14,'Product Master'!$A$7:$A$1000,0))) | L14: =IF($I14="","",INDEX('Product Master'!$M$7:$M$1000,MATCH($I14,'Product Master'!$A$7:$A$1000,0))) | M14: =IF($I14="","",INDEX('Product Master'!$N$7:$N$1000,MATCH($I14,'Product Master'!$A$7:$A$1000,0)))
A15: =IFERROR(INDEX('Product Master'!$A$7:$A$1000,_xlfn.AGGREGATE(15,6,(ROW('Product Master'!$A$7:$A$1000)-ROW('Product Master'!$A$7)+1)/(('Product Master'!$A$7:$A$1000<>"")*('Product Master'!$P$7:$P$1000="Low Stock")),ROWS($A$12:A15))),"") -> PRD-00008 | B15: =IF($A15="","",INDEX('Product Master'!$B$7:$B$1000,MATCH($A15,'Product Master'!$A$7:$A$1000,0))) -> HP LaserJet Pro Printer | C15: =IF($A15="","",INDEX('Product Master'!$C$7:$C$1000,MATCH($A15,'Product Master'!$A$7:$A$1000,0))) -> Electronics | D15: =IF($A15="","",INDEX('Product Master'!$M$7:$M$1000,MATCH($A15,'Product Master'!$A$7:$A$1000,0))) -> 6 | E15: =IF($A15="","",INDEX('Product Master'!$N$7:$N$1000,MATCH($A15,'Product Master'!$A$7:$A$1000,0))) -> 20 | F15: =IF($A15="","",INDEX('Product Master'!$P$7:$P$1000,MATCH($A15,'Product Master'!$A$7:$A$1000,0))) -> Low Stock | I15: =IFERROR(INDEX('Product Master'!$A$7:$A$1000,_xlfn.AGGREGATE(15,6,(ROW('Product Master'!$A$7:$A$1000)-ROW('Product Master'!$A$7)+1)/(('Product Master'!$A$7:$A$1000<>"")*('Product Master'!$P$7:$P$1000="Out of Stock")),ROWS($I$12:I15))),"") | J15: =IF($I15="","",INDEX('Product Master'!$B$7:$B$1000,MATCH($I15,'Product Master'!$A$7:$A$1000,0))) | K15: =IF($I15="","",INDEX('Product Master'!$C$7:$C$1000,MATCH($I15,'Product Master'!$A$7:$A$1000,0))) | L15: =IF($I15="","",INDEX('Product Master'!$M$7:$M$1000,MATCH($I15,'Product Master'!$A$7:$A$1000,0))) | M15: =IF($I15="","",INDEX('Product Master'!$N$7:$N$1000,MATCH($I15,'Product Master'!$A$7:$A$1000,0)))
A16: =IFERROR(INDEX('Product Master'!$A$7:$A$1000,_xlfn.AGGREGATE(15,6,(ROW('Product Master'!$A$7:$A$1000)-ROW('Product Master'!$A$7)+1)/(('Product Master'!$A$7:$A$1000<>"")*('Product Master'!$P$7:$P$1000="Low Stock")),ROWS($A$12:A16))),"") -> PRD-00009 | B16: =IF($A16="","",INDEX('Product Master'!$B$7:$B$1000,MATCH($A16,'Product Master'!$A$7:$A$1000,0))) -> ASUS ZenBook 14 Laptop | C16: =IF($A16="","",INDEX('Product Master'!$C$7:$C$1000,MATCH($A16,'Product Master'!$A$7:$A$1000,0))) -> Electronics | D16: =IF($A16="","",INDEX('Product Master'!$M$7:$M$1000,MATCH($A16,'Product Master'!$A$7:$A$1000,0))) -> 5 | E16: =IF($A16="","",INDEX('Product Master'!$N$7:$N$1000,MATCH($A16,'Product Master'!$A$7:$A$1000,0))) -> 20 | F16: =IF($A16="","",INDEX('Product Master'!$P$7:$P$1000,MATCH($A16,'Product Master'!$A$7:$A$1000,0))) -> Low Stock | I16: =IFERROR(INDEX('Product Master'!$A$7:$A$1000,_xlfn.AGGREGATE(15,6,(ROW('Product Master'!$A$7:$A$1000)-ROW('Product Master'!$A$7)+1)/(('Product Master'!$A$7:$A$1000<>"")*('Product Master'!$P$7:$P$1000="Out of Stock")),ROWS($I$12:I16))),"") | J16: =IF($I16="","",INDEX('Product Master'!$B$7:$B$1000,MATCH($I16,'Product Master'!$A$7:$A$1000,0))) | K16: =IF($I16="","",INDEX('Product Master'!$C$7:$C$1000,MATCH($I16,'Product Master'!$A$7:$A$1000,0))) | L16: =IF($I16="","",INDEX('Product Master'!$M$7:$M$1000,MATCH($I16,'Product Master'!$A$7:$A$1000,0))) | M16: =IF($I16="","",INDEX('Product Master'!$N$7:$N$1000,MATCH($I16,'Product Master'!$A$7:$A$1000,0)))
A17: =IFERROR(INDEX('Product Master'!$A$7:$A$1000,_xlfn.AGGREGATE(15,6,(ROW('Product Master'!$A$7:$A$1000)-ROW('Product Master'!$A$7)+1)/(('Product Master'!$A$7:$A$1000<>"")*('Product Master'!$P$7:$P$1000="Low Stock")),ROWS($A$12:A17))),"") -> PRD-00014 | B17: =IF($A17="","",INDEX('Product Master'!$B$7:$B$1000,MATCH($A17,'Product Master'!$A$7:$A$1000,0))) -> Zara Wool Blend Coat | C17: =IF($A17="","",INDEX('Product Master'!$C$7:$C$1000,MATCH($A17,'Product Master'!$A$7:$A$1000,0))) -> Apparel | D17: =IF($A17="","",INDEX('Product Master'!$M$7:$M$1000,MATCH($A17,'Product Master'!$A$7:$A$1000,0))) -> 10 | E17: =IF($A17="","",INDEX('Product Master'!$N$7:$N$1000,MATCH($A17,'Product Master'!$A$7:$A$1000,0))) -> 20 | F17: =IF($A17="","",INDEX('Product Master'!$P$7:$P$1000,MATCH($A17,'Product Master'!$A$7:$A$1000,0))) -> Low Stock | I17: =IFERROR(INDEX('Product Master'!$A$7:$A$1000,_xlfn.AGGREGATE(15,6,(ROW('Product Master'!$A$7:$A$1000)-ROW('Product Master'!$A$7)+1)/(('Product Master'!$A$7:$A$1000<>"")*('Product Master'!$P$7:$P$1000="Out of Stock")),ROWS($I$12:I17))),"") | J17: =IF($I17="","",INDEX('Product Master'!$B$7:$B$1000,MATCH($I17,'Product Master'!$A$7:$A$1000,0))) | K17: =IF($I17="","",INDEX('Product Master'!$C$7:$C$1000,MATCH($I17,'Product Master'!$A$7:$A$1000,0))) | L17: =IF($I17="","",INDEX('Product Master'!$M$7:$M$1000,MATCH($I17,'Product Master'!$A$7:$A$1000,0))) | M17: =IF($I17="","",INDEX('Product Master'!$N$7:$N$1000,MATCH($I17,'Product Master'!$A$7:$A$1000,0)))
A18: =IFERROR(INDEX('Product Master'!$A$7:$A$1000,_xlfn.AGGREGATE(15,6,(ROW('Product Master'!$A$7:$A$1000)-ROW('Product Master'!$A$7)+1)/(('Product Master'!$A$7:$A$1000<>"")*('Product Master'!$P$7:$P$1000="Low Stock")),ROWS($A$12:A18))),"") -> PRD-00016 | B18: =IF($A18="","",INDEX('Product Master'!$B$7:$B$1000,MATCH($A18,'Product Master'!$A$7:$A$1000,0))) -> Puma Classic Suede Shoes | C18: =IF($A18="","",INDEX('Product Master'!$C$7:$C$1000,MATCH($A18,'Product Master'!$A$7:$A$1000,0))) -> Apparel | D18: =IF($A18="","",INDEX('Product Master'!$M$7:$M$1000,MATCH($A18,'Product Master'!$A$7:$A$1000,0))) -> 15 | E18: =IF($A18="","",INDEX('Product Master'!$N$7:$N$1000,MATCH($A18,'Product Master'!$A$7:$A$1000,0))) -> 20 | F18: =IF($A18="","",INDEX('Product Master'!$P$7:$P$1000,MATCH($A18,'Product Master'!$A$7:$A$1000,0))) -> Low Stock | I18: =IFERROR(INDEX('Product Master'!$A$7:$A$1000,_xlfn.AGGREGATE(15,6,(ROW('Product Master'!$A$7:$A$1000)-ROW('Product Master'!$A$7)+1)/(('Product Master'!$A$7:$A$1000<>"")*('Product Master'!$P$7:$P$1000="Out of Stock")),ROWS($I$12:I18))),"") | J18: =IF($I18="","",INDEX('Product Master'!$B$7:$B$1000,MATCH($I18,'Product Master'!$A$7:$A$1000,0))) | K18: =IF($I18="","",INDEX('Product Master'!$C$7:$C$1000,MATCH($I18,'Product Master'!$A$7:$A$1000,0))) | L18: =IF($I18="","",INDEX('Product Master'!$M$7:$M$1000,MATCH($I18,'Product Master'!$A$7:$A$1000,0))) | M18: =IF($I18="","",INDEX('Product Master'!$N$7:$N$1000,MATCH($I18,'Product Master'!$A$7:$A$1000,0)))
A19: =IFERROR(INDEX('Product Master'!$A$7:$A$1000,_xlfn.AGGREGATE(15,6,(ROW('Product Master'!$A$7:$A$1000)-ROW('Product Master'!$A$7)+1)/(('Product Master'!$A$7:$A$1000<>"")*('Product Master'!$P$7:$P$1000="Low Stock")),ROWS($A$12:A19))),"") -> PRD-00019 | B19: =IF($A19="","",INDEX('Product Master'!$B$7:$B$1000,MATCH($A19,'Product Master'!$A$7:$A$1000,0))) -> Columbia Fleece Jacket | C19: =IF($A19="","",INDEX('Product Master'!$C$7:$C$1000,MATCH($A19,'Product Master'!$A$7:$A$1000,0))) -> Apparel | D19: =IF($A19="","",INDEX('Product Master'!$M$7:$M$1000,MATCH($A19,'Product Master'!$A$7:$A$1000,0))) -> 12 | E19: =IF($A19="","",INDEX('Product Master'!$N$7:$N$1000,MATCH($A19,'Product Master'!$A$7:$A$1000,0))) -> 20 | F19: =IF($A19="","",INDEX('Product Master'!$P$7:$P$1000,MATCH($A19,'Product Master'!$A$7:$A$1000,0))) -> Low Stock | I19: =IFERROR(INDEX('Product Master'!$A$7:$A$1000,_xlfn.AGGREGATE(15,6,(ROW('Product Master'!$A$7:$A$1000)-ROW('Product Master'!$A$7)+1)/(('Product Master'!$A$7:$A$1000<>"")*('Product Master'!$P$7:$P$1000="Out of Stock")),ROWS($I$12:I19))),"") | J19: =IF($I19="","",INDEX('Product Master'!$B$7:$B$1000,MATCH($I19,'Product Master'!$A$7:$A$1000,0))) | K19: =IF($I19="","",INDEX('Product Master'!$C$7:$C$1000,MATCH($I19,'Product Master'!$A$7:$A$1000,0))) | L19: =IF($I19="","",INDEX('Product Master'!$M$7:$M$1000,MATCH($I19,'Product Master'!$A$7:$A$1000,0))) | M19: =IF($I19="","",INDEX('Product Master'!$N$7:$N$1000,MATCH($I19,'Product Master'!$A$7:$A$1000,0)))
A20: =IFERROR(INDEX('Product Master'!$A$7:$A$1000,_xlfn.AGGREGATE(15,6,(ROW('Product Master'!$A$7:$A$1000)-ROW('Product Master'!$A$7)+1)/(('Product Master'!$A$7:$A$1000<>"")*('Product Master'!$P$7:$P$1000="Low Stock")),ROWS($A$12:A20))),"") | B20: =IF($A20="","",INDEX('Product Master'!$B$7:$B$1000,MATCH($A20,'Product Master'!$A$7:$A$1000,0))) | C20: =IF($A20="","",INDEX('Product Master'!$C$7:$C$1000,MATCH($A20,'Product Master'!$A$7:$A$1000,0))) | D20: =IF($A20="","",INDEX('Product Master'!$M$7:$M$1000,MATCH($A20,'Product Master'!$A$7:$A$1000,0))) | E20: =IF($A20="","",INDEX('Product Master'!$N$7:$N$1000,MATCH($A20,'Product Master'!$A$7:$A$1000,0))) | F20: =IF($A20="","",INDEX('Product Master'!$P$7:$P$1000,MATCH($A20,'Product Master'!$A$7:$A$1000,0))) | I20: =IFERROR(INDEX('Product Master'!$A$7:$A$1000,_xlfn.AGGREGATE(15,6,(ROW('Product Master'!$A$7:$A$1000)-ROW('Product Master'!$A$7)+1)/(('Product Master'!$A$7:$A$1000<>"")*('Product Master'!$P$7:$P$1000="Out of Stock")),ROWS($I$12:I20))),"") | J20: =IF($I20="","",INDEX('Product Master'!$B$7:$B$1000,MATCH($I20,'Product Master'!$A$7:$A$1000,0))) | K20: =IF($I20="","",INDEX('Product Master'!$C$7:$C$1000,MATCH($I20,'Product Master'!$A$7:$A$1000,0))) | L20: =IF($I20="","",INDEX('Product Master'!$M$7:$M$1000,MATCH($I20,'Product Master'!$A$7:$A$1000,0))) | M20: =IF($I20="","",INDEX('Product Master'!$N$7:$N$1000,MATCH($I20,'Product Master'!$A$7:$A$1000,0)))
A21: =IFERROR(INDEX('Product Master'!$A$7:$A$1000,_xlfn.AGGREGATE(15,6,(ROW('Product Master'!$A$7:$A$1000)-ROW('Product Master'!$A$7)+1)/(('Product Master'!$A$7:$A$1000<>"")*('Product Master'!$P$7:$P$1000="Low Stock")),ROWS($A$12:A21))),"") | B21: =IF($A21="","",INDEX('Product Master'!$B$7:$B$1000,MATCH($A21,'Product Master'!$A$7:$A$1000,0))) | C21: =IF($A21="","",INDEX('Product Master'!$C$7:$C$1000,MATCH($A21,'Product Master'!$A$7:$A$1000,0))) | D21: =IF($A21="","",INDEX('Product Master'!$M$7:$M$1000,MATCH($A21,'Product Master'!$A$7:$A$1000,0))) | E21: =IF($A21="","",INDEX('Product Master'!$N$7:$N$1000,MATCH($A21,'Product Master'!$A$7:$A$1000,0))) | F21: =IF($A21="","",INDEX('Product Master'!$P$7:$P$1000,MATCH($A21,'Product Master'!$A$7:$A$1000,0))) | I21: =IFERROR(INDEX('Product Master'!$A$7:$A$1000,_xlfn.AGGREGATE(15,6,(ROW('Product Master'!$A$7:$A$1000)-ROW('Product Master'!$A$7)+1)/(('Product Master'!$A$7:$A$1000<>"")*('Product Master'!$P$7:$P$1000="Out of Stock")),ROWS($I$12:I21))),"") | J21: =IF($I21="","",INDEX('Product Master'!$B$7:$B$1000,MATCH($I21,'Product Master'!$A$7:$A$1000,0))) | K21: =IF($I21="","",INDEX('Product Master'!$C$7:$C$1000,MATCH($I21,'Product Master'!$A$7:$A$1000,0))) | L21: =IF($I21="","",INDEX('Product Master'!$M$7:$M$1000,MATCH($I21,'Product Master'!$A$7:$A$1000,0))) | M21: =IF($I21="","",INDEX('Product Master'!$N$7:$N$1000,MATCH($I21,'Product Master'!$A$7:$A$1000,0)))
A22: =IFERROR(INDEX('Product Master'!$A$7:$A$1000,_xlfn.AGGREGATE(15,6,(ROW('Product Master'!$A$7:$A$1000)-ROW('Product Master'!$A$7)+1)/(('Product Master'!$A$7:$A$1000<>"")*('Product Master'!$P$7:$P$1000="Low Stock")),ROWS($A$12:A22))),"") | B22: =IF($A22="","",INDEX('Product Master'!$B$7:$B$1000,MATCH($A22,'Product Master'!$A$7:$A$1000,0))) | C22: =IF($A22="","",INDEX('Product Master'!$C$7:$C$1000,MATCH($A22,'Product Master'!$A$7:$A$1000,0))) | D22: =IF($A22="","",INDEX('Product Master'!$M$7:$M$1000,MATCH($A22,'Product Master'!$A$7:$A$1000,0))) | E22: =IF($A22="","",INDEX('Product Master'!$N$7:$N$1000,MATCH($A22,'Product Master'!$A$7:$A$1000,0))) | F22: =IF($A22="","",INDEX('Product Master'!$P$7:$P$1000,MATCH($A22,'Product Master'!$A$7:$A$1000,0))) | I22: =IFERROR(INDEX('Product Master'!$A$7:$A$1000,_xlfn.AGGREGATE(15,6,(ROW('Product Master'!$A$7:$A$1000)-ROW('Product Master'!$A$7)+1)/(('Product Master'!$A$7:$A$1000<>"")*('Product Master'!$P$7:$P$1000="Out of Stock")),ROWS($I$12:I22))),"") | J22: =IF($I22="","",INDEX('Product Master'!$B$7:$B$1000,MATCH($I22,'Product Master'!$A$7:$A$1000,0))) | K22: =IF($I22="","",INDEX('Product Master'!$C$7:$C$1000,MATCH($I22,'Product Master'!$A$7:$A$1000,0))) | L22: =IF($I22="","",INDEX('Product Master'!$M$7:$M$1000,MATCH($I22,'Product Master'!$A$7:$A$1000,0))) | M22: =IF($I22="","",INDEX('Product Master'!$N$7:$N$1000,MATCH($I22,'Product Master'!$A$7:$A$1000,0)))
A23: =IFERROR(INDEX('Product Master'!$A$7:$A$1000,_xlfn.AGGREGATE(15,6,(ROW('Product Master'!$A$7:$A$1000)-ROW('Product Master'!$A$7)+1)/(('Product Master'!$A$7:$A$1000<>"")*('Product Master'!$P$7:$P$1000="Low Stock")),ROWS($A$12:A23))),"") | B23: =IF($A23="","",INDEX('Product Master'!$B$7:$B$1000,MATCH($A23,'Product Master'!$A$7:$A$1000,0))) | C23: =IF($A23="","",INDEX('Product Master'!$C$7:$C$1000,MATCH($A23,'Product Master'!$A$7:$A$1000,0))) | D23: =IF($A23="","",INDEX('Product Master'!$M$7:$M$1000,MATCH($A23,'Product Master'!$A$7:$A$1000,0))) | E23: =IF($A23="","",INDEX('Product Master'!$N$7:$N$1000,MATCH($A23,'Product Master'!$A$7:$A$1000,0))) | F23: =IF($A23="","",INDEX('Product Master'!$P$7:$P$1000,MATCH($A23,'Product Master'!$A$7:$A$1000,0))) | I23: =IFERROR(INDEX('Product Master'!$A$7:$A$1000,_xlfn.AGGREGATE(15,6,(ROW('Product Master'!$A$7:$A$1000)-ROW('Product Master'!$A$7)+1)/(('Product Master'!$A$7:$A$1000<>"")*('Product Master'!$P$7:$P$1000="Out of Stock")),ROWS($I$12:I23))),"") | J23: =IF($I23="","",INDEX('Product Master'!$B$7:$B$1000,MATCH($I23,'Product Master'!$A$7:$A$1000,0))) | K23: =IF($I23="","",INDEX('Product Master'!$C$7:$C$1000,MATCH($I23,'Product Master'!$A$7:$A$1000,0))) | L23: =IF($I23="","",INDEX('Product Master'!$M$7:$M$1000,MATCH($I23,'Product Master'!$A$7:$A$1000,0))) | M23: =IF($I23="","",INDEX('Product Master'!$N$7:$N$1000,MATCH($I23,'Product Master'!$A$7:$A$1000,0)))
... A1000: =IFERROR(INDEX('Product Master'!$A$7:$A$1000,_xlfn.AGGREGATE(15,6,(ROW('Product Master'!$A$7:$A$1000)-ROW('Product Master'!$A$7)+1)/(('Product Master'!$A$7:$A$1000<>"")*('Product Master'!$P$7:$P$1000="Low Stock")),ROWS($A$12:A1000))),"") | B1000: =IF($A1000="","",INDEX('Product Master'!$B$7:$B$1000,MATCH($A1000,'Product Master'!$A$7:$A$1000,0))) | C1000: =IF($A1000="","",INDEX('Product Master'!$C$7:$C$1000,MATCH($A1000,'Product Master'!$A$7:$A$1000,0))) | D1000: =IF($A1000="","",INDEX('Product Master'!$M$7:$M$1000,MATCH($A1000,'Product Master'!$A$7:$A$1000,0))) | E1000: =IF($A1000="","",INDEX('Product Master'!$N$7:$N$1000,MATCH($A1000,'Product Master'!$A$7:$A$1000,0))) | F1000: =IF($A1000="","",INDEX('Product Master'!$P$7:$P$1000,MATCH($A1000,'Product Master'!$A$7:$A$1000,0))) | I1000: =IFERROR(INDEX('Product Master'!$A$7:$A$1000,_xlfn.AGGREGATE(15,6,(ROW('Product Master'!$A$7:$A$1000)-ROW('Product Master'!$A$7)+1)/(('Product Master'!$A$7:$A$1000<>"")*('Product Master'!$P$7:$P$1000="Out of Stock")),ROWS($I$12:I1000))),"") | J1000: =IF($I1000="","",INDEX('Product Master'!$B$7:$B$1000,MATCH($I1000,'Product Master'!$A$7:$A$1000,0))) | K1000: =IF($I1000="","",INDEX('Product Master'!$C$7:$C$1000,MATCH($I1000,'Product Master'!$A$7:$A$1000,0))) | L1000: =IF($I1000="","",INDEX('Product Master'!$M$7:$M$1000,MATCH($I1000,'Product Master'!$A$7:$A$1000,0))) | M1000: =IF($I1000="","",INDEX('Product Master'!$N$7:$N$1000,MATCH($I1000,'Product Master'!$A$7:$A$1000,0)))

Sheet Product Master
A1: PRODUCT MASTER REGISTRY
A4: =HYPERLINK("#'Dashboard'!A1", "📊 Dashboard") -> 📊 Dashboard | D4: =HYPERLINK("#'Product Master'!A1", "📦 Product Master") -> 📦 Product Master | H4: =HYPERLINK("#'Purchase Entry'!A1", "📥 Purchase Entry") -> 📥 Purchase Entry | L4: =HYPERLINK("#'Sales Entry'!A1", "📤 Sales Entry") -> 📤 Sales Entry | O4: =HYPERLINK("#'Supplier Management'!A1", "🤝 Suppliers") -> 🤝 Suppliers | R4: =HYPERLINK("#'Reports'!A1", "📈 Reports") -> 📈 Reports
A6: Product ID | B6: Product Name | C6: Category | D6: Brand | E6: Supplier | F6: Unit of Measure | G6: Unit Price | H6: Cost Price | I6: Selling Price | J6: Initial Stock | K6: Purchases Qty | L6: Sales Qty | M6: Current Stock | N6: Reorder Level | O6: Storage Location | P6: Status | Q6: Warranty Period | R6: Quantity per Set | S6: Set Price | T6: Stock Value | U6: Total Sales Value | V6: Margin %
A7: =IF(ISBLANK(B7), "", "PRD-" & TEXT(ROW()-6, "00000")) -> PRD-00001 | B7: Sony WH-1000XM4 Headphones | C7: Electronics | D7: Sony | E7: Apex Distributors | F7: pcs | G7: 250 | H7: 180 | I7: =G7 * R7 -> 250 | J7: 15 | K7: =SUMIF('Purchase Entry'!$C:$C, $A7, 'Purchase Entry'!$F:$F) -> 25 | L7: =SUMIF('Sales Entry'!$C:$C, $A7, 'Sales Entry'!$E:$E) -> 20 | M7: =J7 + K7 - L7 -> 20 | N7: 5 | O7: Aisle A | P7: =IF(M7<=0, "Out of Stock", IF(M7<=N7, "Low Stock", "In Stock")) -> In Stock | Q7: 12 Months | R7: 1 | S7: =IF(R7>1, I7 * 0.95, I7) -> 250 | T7: =M7 * H7 -> 3600 | U7: =L7 * I7 -> 5000 | V7: =IF(U7>0, (U7 - (L7*H7)) / U7, 0) -> 0.28
A8: =IF(ISBLANK(B8), "", "PRD-" & TEXT(ROW()-6, "00000")) -> PRD-00002 | B8: Samsung 27" Curved Monitor | C8: Electronics | D8: Samsung | E8: Apex Distributors | F8: pcs | G8: 180 | H8: 120 | I8: =G8 * R8 -> 180 | J8: 10 | K8: =SUMIF('Purchase Entry'!$C:$C, $A8, 'Purchase Entry'!$F:$F) -> 25 | L8: =SUMIF('Sales Entry'!$C:$C, $A8, 'Sales Entry'!$E:$E) -> 6 | M8: =J8 + K8 - L8 -> 29 | N8: 3 | O8: Aisle A | P8: =IF(M8<=0, "Out of Stock", IF(M8<=N8, "Low Stock", "In Stock")) -> In Stock | Q8: 24 Months | R8: 1 | S8: =IF(R8>1, I8 * 0.95, I8) -> 180 | T8: =M8 * H8 -> 3480 | U8: =L8 * I8 -> 1080 | V8: =IF(U8>0, (U8 - (L8*H8)) / U8, 0) -> 0.33333333
A9: =IF(ISBLANK(B9), "", "PRD-" & TEXT(ROW()-6, "00000")) -> PRD-00003 | B9: Apple iPad Air (64GB) | C9: Electronics | D9: Apple | E9: Global Trade Co. | F9: pcs | G9: 549 | H9: 420 | I9: =G9 * R9 -> 549 | J9: 8 | K9: =SUMIF('Purchase Entry'!$C:$C, $A9, 'Purchase Entry'!$F:$F) -> 15 | L9: =SUMIF('Sales Entry'!$C:$C, $A9, 'Sales Entry'!$E:$E) -> 6 | M9: =J9 + K9 - L9 -> 17 | N9: 20 | O9: Aisle A | P9: =IF(M9<=0, "Out of Stock", IF(M9<=N9, "Low Stock", "In Stock")) -> Low Stock | Q9: 12 Months | R9: 1 | S9: =IF(R9>1, I9 * 0.95, I9) -> 549 | T9: =M9 * H9 -> 7140 | U9: =L9 * I9 -> 3294 | V9: =IF(U9>0, (U9 - (L9*H9)) / U9, 0) -> 0.23497268
A10: =IF(ISBLANK(B10), "", "PRD-" & TEXT(ROW()-6, "00000")) -> PRD-00004 | B10: Dell Wireless Keyboard Combo | C10: Electronics | D10: Dell | E10: Apex Distributors | F10: pcs | G10: 45 | H10: 25 | I10: =G10 * R10 -> 45 | J10: 25 | K10: =SUMIF('Purchase Entry'!$C:$C, $A10, 'Purchase Entry'!$F:$F) -> 0 | L10: =SUMIF('Sales Entry'!$C:$C, $A10, 'Sales Entry'!$E:$E) -> 0 | M10: =J10 + K10 - L10 -> 25 | N10: 20 | O10: Aisle A | P10: =IF(M10<=0, "Out of Stock", IF(M10<=N10, "Low Stock", "In Stock")) -> In Stock | Q10: 12 Months | R10: 1 | S10: =IF(R10>1, I10 * 0.95, I10) -> 45 | T10: =M10 * H10 -> 625 | U10: =L10 * I10 -> 0 | V10: =IF(U10>0, (U10 - (L10*H10)) / U10, 0) -> 0
A11: =IF(ISBLANK(B11), "", "PRD-" & TEXT(ROW()-6, "00000")) -> PRD-00005 | B11: Logitech C920 HD Pro Webcam | C11: Electronics | D11: Logitech | E11: Apex Distributors | F11: pcs | G11: 79 | H11: 45 | I11: =G11 * R11 -> 79 | J11: 12 | K11: =SUMIF('Purchase Entry'!$C:$C, $A11, 'Purchase Entry'!$F:$F) -> 0 | L11: =SUMIF('Sales Entry'!$C:$C, $A11, 'Sales Entry'!$E:$E) -> 0 | M11: =J11 + K11 - L11 -> 12 | N11: 20 | O11: Aisle A | P11: =IF(M11<=0, "Out of Stock", IF(M11<=N11, "Low Stock", "In Stock")) -> Low Stock | Q11: 12 Months | R11: 1 | S11: =IF(R11>1, I11 * 0.95, I11) -> 79 | T11: =M11 * H11 -> 540 | U11: =L11 * I11 -> 0 | V11: =IF(U11>0, (U11 - (L11*H11)) / U11, 0) -> 0
A12: =IF(ISBLANK(B12), "", "PRD-" & TEXT(ROW()-6, "00000")) -> PRD-00006 | B12: SanDisk Extreme 128GB USB-C | C12: Electronics | D12: SanDisk | E12: Summit Wholesale | F12: pcs | G12: 29.99 | H12: 15 | I12: =G12 * R12 -> 29.99 | J12: 40 | K12: =SUMIF('Purchase Entry'!$C:$C, $A12, 'Purchase Entry'!$F:$F) -> 35 | L12: =SUMIF('Sales Entry'!$C:$C, $A12, 'Sales Entry'!$E:$E) -> 11 | M12: =J12 + K12 - L12 -> 64 | N12: 20 | O12: Aisle A | P12: =IF(M12<=0, "Out of Stock", IF(M12<=N12, "Low Stock", "In Stock")) -> In Stock | Q12: 60 Months | R12: 1 | S12: =IF(R12>1, I12 * 0.95, I12) -> 29.99 | T12: =M12 * H12 -> 960 | U12: =L12 * I12 -> 329.89 | V12: =IF(U12>0, (U12 - (L12*H12)) / U12, 0) -> 0.49983328
A13: =IF(ISBLANK(B13), "", "PRD-" & TEXT(ROW()-6, "00000")) -> PRD-00007 | B13: Anker PowerCore 26800mAh | C13: Electronics | D13: Anker | E13: Summit Wholesale | F13: pcs | G13: 59.99 | H13: 35 | I13: =G13 * R13 -> 59.99 | J13: 18 | K13: =SUMIF('Purchase Entry'!$C:$C, $A13, 'Purchase Entry'!$F:$F) -> 0 | L13: =SUMIF('Sales Entry'!$C:$C, $A13, 'Sales Entry'!$E:$E) -> 0 | M13: =J13 + K13 - L13 -> 18 | N13: 20 | O13: Aisle A | P13: =IF(M13<=0, "Out of Stock", IF(M13<=N13, "Low Stock", "In Stock")) -> Low Stock | Q13: 18 Months | R13: 1 | S13: =IF(R13>1, I13 * 0.95, I13) -> 59.99 | T13: =M13 * H13 -> 630 | U13: =L13 * I13 -> 0 | V13: =IF(U13>0, (U13 - (L13*H13)) / U13, 0) -> 0
A14: =IF(ISBLANK(B14), "", "PRD-" & TEXT(ROW()-6, "00000")) -> PRD-00008 | B14: HP LaserJet Pro Printer | C14: Electronics | D14: HP | E14: Prime Logistics | F14: pcs | G14: 229 | H14: 150 | I14: =G14 * R14 -> 229 | J14: 6 | K14: =SUMIF('Purchase Entry'!$C:$C, $A14, 'Purchase Entry'!$F:$F) -> 0 | L14: =SUMIF('Sales Entry'!$C:$C, $A14, 'Sales Entry'!$E:$E) -> 0 | M14: =J14 + K14 - L14 -> 6 | N14: 20 | O14: Warehouse | P14: =IF(M14<=0, "Out of Stock", IF(M14<=N14, "Low Stock", "In Stock")) -> Low Stock | Q14: 12 Months | R14: 1 | S14: =IF(R14>1, I14 * 0.95, I14) -> 229 | T14: =M14 * H14 -> 900 | U14: =L14 * I14 -> 0 | V14: =IF(U14>0, (U14 - (L14*H14)) / U14, 0) -> 0
A15: =IF(ISBLANK(B15), "", "PRD-" & TEXT(ROW()-6, "00000")) -> PRD-00009 | B15: ASUS ZenBook 14 Laptop | C15: Electronics | D15: ASUS | E15: Global Trade Co. | F15: pcs | G15: 899.99 | H15: 650 | I15: =G15 * R15 -> 899.99 | J15: 5 | K15: =SUMIF('Purchase Entry'!$C:$C, $A15, 'Purchase Entry'!$F:$F) -> 0 | L15: =SUMIF('Sales Entry'!$C:$C, $A15, 'Sales Entry'!$E:$E) -> 0 | M15: =J15 + K15 - L15 -> 5 | N15: 20 | O15: Aisle A | P15: =IF(M15<=0, "Out of Stock", IF(M15<=N15, "Low Stock", "In Stock")) -> Low Stock | Q15: 12 Months | R15: 1 | S15: =IF(R15>1, I15 * 0.95, I15) -> 899.99 | T15: =M15 * H15 -> 3250 | U15: =L15 * I15 -> 0 | V15: =IF(U15>0, (U15 - (L15*H15)) / U15, 0) -> 0
A16: =IF(ISBLANK(B16), "", "PRD-" & TEXT(ROW()-6, "00000")) -> PRD-00010 | B16: Belkin 12-Outlet Surge Protector | C16: Electronics | D16: Belkin | E16: Summit Wholesale | F16: pcs | G16: 24.99 | H16: 12 | I16: =G16 * R16 -> 24.99 | J16: 30 | K16: =SUMIF('Purchase Entry'!$C:$C, $A16, 'Purchase Entry'!$F:$F) -> 0 | L16: =SUMIF('Sales Entry'!$C:$C, $A16, 'Sales Entry'!$E:$E) -> 0 | M16: =J16 + K16 - L16 -> 30 | N16: 20 | O16: Aisle A | P16: =IF(M16<=0, "Out of Stock", IF(M16<=N16, "Low Stock", "In Stock")) -> In Stock | Q16: Lifetime | R16: 1 | S16: =IF(R16>1, I16 * 0.95, I16) -> 24.99 | T16: =M16 * H16 -> 360 | U16: =L16 * I16 -> 0 | V16: =IF(U16>0, (U16 - (L16*H16)) / U16, 0) -> 0
A17: =IF(ISBLANK(B17), "", "PRD-" & TEXT(ROW()-6, "00000")) -> PRD-00011 | B17: Nike Air Max Sneakers | C17: Apparel | D17: Nike | E17: Summit Wholesale | F17: pcs | G17: 120 | H17: 70 | I17: =G17 * R17 -> 120 | J17: 20 | K17: =SUMIF('Purchase Entry'!$C:$C, $A17, 'Purchase Entry'!$F:$F) -> 25 | L17: =SUMIF('Sales Entry'!$C:$C, $A17, 'Sales Entry'!$E:$E) -> 12 | M17: =J17 + K17 - L17 -> 33 | N17: 20 | O17: Aisle B | P17: =IF(M17<=0, "Out of Stock", IF(M17<=N17, "Low Stock", "In Stock")) -> In Stock | Q17: 0 Months | R17: 1 | S17: =IF(R17>1, I17 * 0.95, I17) -> 120 | T17: =M17 * H17 -> 2310 | U17: =L17 * I17 -> 1440 | V17: =IF(U17>0, (U17 - (L17*H17)) / U17, 0) -> 0.41666667
A18: =IF(ISBLANK(B18), "", "PRD-" & TEXT(ROW()-6, "00000")) -> PRD-00012 | B18: Adidas Essentials Hoodie | C18: Apparel | D18: Adidas | E18: Summit Wholesale | F18: pcs | G18: 50 | H18: 25 | I18: =G18 * R18 -> 50 | J18: 30 | K18: =SUMIF('Purchase Entry'!$C:$C, $A18, 'Purchase Entry'!$F:$F) -> 0 | L18: =SUMIF('Sales Entry'!$C:$C, $A18, 'Sales Entry'!$E:$E) -> 0 | M18: =J18 + K18 - L18 -> 30 | N18: 20 | O18: Aisle B | P18: =IF(M18<=0, "Out of Stock", IF(M18<=N18, "Low Stock", "In Stock")) -> In Stock | Q18: 0 Months | R18: 1 | S18: =IF(R18>1, I18 * 0.95, I18) -> 50 | T18: =M18 * H18 -> 750 | U18: =L18 * I18 -> 0 | V18: =IF(U18>0, (U18 - (L18*H18)) / U18, 0) -> 0
... A56: =IF(ISBLANK(B56), "", "PRD-" & TEXT(ROW()-6, "00000")) -> PRD-00050 | B56: Hamilton Beach Electric Kettle | C56: Home & Kitchen | D56: Hamilton Beach | E56: Summit Wholesale | F56: pcs | G56: 21.99 | H56: 12 | I56: =G56 * R56 -> 21.99 | J56: 22 | K56: =SUMIF('Purchase Entry'!$C:$C, $A56, 'Purchase Entry'!$F:$F) -> 0 | L56: =SUMIF('Sales Entry'!$C:$C, $A56, 'Sales Entry'!$E:$E) -> 0 | M56: =J56 + K56 - L56 -> 22 | N56: 6 | O56: Aisle E | P56: =IF(M56<=0, "Out of Stock", IF(M56<=N56, "Low Stock", "In Stock")) -> In Stock | Q56: 12 Months | R56: 1 | S56: =IF(R56>1, I56 * 0.95, I56) -> 21.99 | T56: =M56 * H56 -> 264 | U56: =L56 * I56 -> 0 | V56: =IF(U56>0, (U56 - (L56*H56)) / U56, 0) -> 0

Sheet Purchase Entry
A1: PURCHASE ENTRY LEDGER
A4: =HYPERLINK("#'Dashboard'!A1", "📊 Dashboard") -> 📊 Dashboard | D4: =HYPERLINK("#'Product Master'!A1", "📦 Product Master") -> 📦 Product Master | H4: =HYPERLINK("#'Purchase Entry'!A1", "📥 Purchase Entry") -> 📥 Purchase Entry | I4: =HYPERLINK("#'Sales Entry'!A1", "📤 Sales Entry") -> 📤 Sales Entry | L4: =HYPERLINK("#'Supplier Management'!A1", "🤝 Suppliers") -> 🤝 Suppliers | O4: =HYPERLINK("#'Reports'!A1", "📈 Reports") -> 📈 Reports
A6: Purchase ID | B6: Date | C6: Product ID | D6: Product Name | E6: Supplier Name | F6: Quantity Purchased | G6: Cost Price | H6: Total Cost
A7: ="PUR-" & TEXT(ROW()-6, "00000") -> PUR-00001 | B7: 46037 | C7: PRD-00001 | D7: =IF(C7="", "", VLOOKUP(C7, 'Product Master'!$A:$H, 2, FALSE)) -> Sony WH-1000XM4 Headphones | E7: =IFERROR(VLOOKUP(C7, ProductMaster, 5, FALSE), "") | F7: 10 | G7: =IFERROR(VLOOKUP(C7, ProductMaster, 8, FALSE), 0) -> 0 | H7: =F7 * G7 -> 0
A8: ="PUR-" & TEXT(ROW()-6, "00000") -> PUR-00002 | B8: 46042 | C8: PRD-00002 | D8: =IF(C8="", "", VLOOKUP(C8, 'Product Master'!$A:$H, 2, FALSE)) -> Samsung 27" Curved Monitor | E8: =IF(C7="", "", VLOOKUP(C7, 'Product Master'!$A:$H, 5, FALSE)) -> Apex Distributors | F8: 15 | G8: =IF(C7="", "", VLOOKUP(C7, 'Product Master'!$A:$H, 8, FALSE)) -> 180 | H8: =F8 * G8 -> 2700
A9: ="PUR-" & TEXT(ROW()-6, "00000") -> PUR-00003 | B9: 46058 | C9: PRD-00003 | D9: =IF(C9="", "", VLOOKUP(C9, 'Product Master'!$A:$H, 2, FALSE)) -> Apple iPad Air (64GB) | E9: =IF(C8="", "", VLOOKUP(C8, 'Product Master'!$A:$H, 5, FALSE)) -> Apex Distributors | F9: 5 | G9: =IF(C8="", "", VLOOKUP(C8, 'Product Master'!$A:$H, 8, FALSE)) -> 120 | H9: =F9 * G9 -> 600
A10: ="PUR-" & TEXT(ROW()-6, "00000") -> PUR-00004 | B10: 46063 | C10: PRD-00006 | D10: =IF(C10="", "", VLOOKUP(C10, 'Product Master'!$A:$H, 2, FALSE)) -> SanDisk Extreme 128GB USB-C | E10: =IF(C9="", "", VLOOKUP(C9, 'Product Master'!$A:$H, 5, FALSE)) -> Global Trade Co. | F10: 15 | G10: =IF(C9="", "", VLOOKUP(C9, 'Product Master'!$A:$H, 8, FALSE)) -> 420 | H10: =F10 * G10 -> 6300
A11: ="PUR-" & TEXT(ROW()-6, "00000") -> PUR-00005 | B11: 46081 | C11: PRD-00011 | D11: =IF(C11="", "", VLOOKUP(C11, 'Product Master'!$A:$H, 2, FALSE)) -> Nike Air Max Sneakers | E11: =IF(C10="", "", VLOOKUP(C10, 'Product Master'!$A:$H, 5, FALSE)) -> Summit Wholesale | F11: 10 | G11: =IF(C10="", "", VLOOKUP(C10, 'Product Master'!$A:$H, 8, FALSE)) -> 15 | H11: =F11 * G11 -> 150
A12: ="PUR-" & TEXT(ROW()-6, "00000") -> PUR-00006 | B12: 46082 | C12: PRD-00015 | D12: =IF(C12="", "", VLOOKUP(C12, 'Product Master'!$A:$H, 2, FALSE)) -> H&M Basic Crewneck T-Shirt | E12: =IF(C11="", "", VLOOKUP(C11, 'Product Master'!$A:$H, 5, FALSE)) -> Summit Wholesale | F12: 30 | G12: =IF(C11="", "", VLOOKUP(C11, 'Product Master'!$A:$H, 8, FALSE)) -> 70 | H12: =F12 * G12 -> 2100
A13: ="PUR-" & TEXT(ROW()-6, "00000") -> PUR-00007 | B13: 46086 | C13: PRD-00021 | D13: =IF(C13="", "", VLOOKUP(C13, 'Product Master'!$A:$H, 2, FALSE)) -> Nestlé Pure Life Water (24pk) | E13: =IF(C12="", "", VLOOKUP(C12, 'Product Master'!$A:$H, 5, FALSE)) -> Summit Wholesale | F13: 50 | G13: =IF(C12="", "", VLOOKUP(C12, 'Product Master'!$A:$H, 8, FALSE)) -> 8 | H13: =F13 * G13 -> 400
A14: ="PUR-" & TEXT(ROW()-6, "00000") -> PUR-00008 | B14: 46091 | C14: PRD-00031 | D14: =IF(C14="", "", VLOOKUP(C14, 'Product Master'!$A:$H, 2, FALSE)) -> Pfizer Advil Pain Reliever (100ct) | E14: =IF(C13="", "", VLOOKUP(C13, 'Product Master'!$A:$H, 5, FALSE)) -> Prime Logistics | F14: 20 | G14: =IF(C13="", "", VLOOKUP(C13, 'Product Master'!$A:$H, 8, FALSE)) -> 2.5 | H14: =F14 * G14 -> 50
A15: ="PUR-" & TEXT(ROW()-6, "00000") -> PUR-00009 | B15: 46096 | C15: PRD-00041 | D15: =IF(C15="", "", VLOOKUP(C15, 'Product Master'!$A:$H, 2, FALSE)) -> Dyson V11 Cordless Vacuum | E15: =IF(C14="", "", VLOOKUP(C14, 'Product Master'!$A:$H, 5, FALSE)) -> BioPharma Supplies | F15: 3 | G15: =IF(C14="", "", VLOOKUP(C14, 'Product Master'!$A:$H, 8, FALSE)) -> 4.5 | H15: =F15 * G15 -> 13.5
A16: ="PUR-" & TEXT(ROW()-6, "00000") -> PUR-00010 | B16: 46113 | C16: PRD-00001 | D16: =IF(C16="", "", VLOOKUP(C16, 'Product Master'!$A:$H, 2, FALSE)) -> Sony WH-1000XM4 Headphones | E16: =IF(C15="", "", VLOOKUP(C15, 'Product Master'!$A:$H, 5, FALSE)) -> Global Trade Co. | F16: 15 | G16: =IF(C15="", "", VLOOKUP(C15, 'Product Master'!$A:$H, 8, FALSE)) -> 380 | H16: =F16 * G16 -> 5700
A17: ="PUR-" & TEXT(ROW()-6, "00000") -> PUR-00011 | B17: 46117 | C17: PRD-00002 | D17: =IF(C17="", "", VLOOKUP(C17, 'Product Master'!$A:$H, 2, FALSE)) -> Samsung 27" Curved Monitor | E17: =IF(C16="", "", VLOOKUP(C16, 'Product Master'!$A:$H, 5, FALSE)) -> Apex Distributors | F17: 10 | G17: =IF(C16="", "", VLOOKUP(C16, 'Product Master'!$A:$H, 8, FALSE)) -> 180 | H17: =F17 * G17 -> 1800
A18: ="PUR-" & TEXT(ROW()-6, "00000") -> PUR-00012 | B18: 46122 | C18: PRD-00003 | D18: =IF(C18="", "", VLOOKUP(C18, 'Product Master'!$A:$H, 2, FALSE)) -> Apple iPad Air (64GB) | E18: =IF(C17="", "", VLOOKUP(C17, 'Product Master'!$A:$H, 5, FALSE)) -> Apex Distributors | F18: 10 | G18: =IF(C17="", "", VLOOKUP(C17, 'Product Master'!$A:$H, 8, FALSE)) -> 120 | H18: =F18 * G18 -> 1200
A19: ="PUR-" & TEXT(ROW()-6, "00000") -> PUR-00013 | B19: 46127 | C19: PRD-00006 | D19: =IF(C19="", "", VLOOKUP(C19, 'Product Master'!$A:$H, 2, FALSE)) -> SanDisk Extreme 128GB USB-C | E19: =IF(C18="", "", VLOOKUP(C18, 'Product Master'!$A:$H, 5, FALSE)) -> Global Trade Co. | F19: 20 | G19: =IF(C18="", "", VLOOKUP(C18, 'Product Master'!$A:$H, 8, FALSE)) -> 420 | H19: =F19 * G19 -> 8400
... A24: ="PUR-" & TEXT(ROW()-6, "00000") -> PUR-00018 | B24: 46157 | C24: PRD-00041 | D24: =IF(C24="", "", VLOOKUP(C24, 'Product Master'!$A:$H, 2, FALSE)) -> Dyson V11 Cordless Vacuum | E24: =IF(C23="", "", VLOOKUP(C23, 'Product Master'!$A:$H, 5, FALSE)) -> BioPharma Supplies | F24: 5 | G24: =IF(C23="", "", VLOOKUP(C23, 'Product Master'!$A:$H, 8, FALSE)) -> 4.5 | H24: =F24 * G24 -> 22.5

Sheet Sales Entry
A1: SALES LEDGER LOG
A4: =HYPERLINK("#'Dashboard'!A1", "📊 Dashboard") -> 📊 Dashboard | D4: =HYPERLINK("#'Product Master'!A1", "📦 Product Master") -> 📦 Product Master | H4: =HYPERLINK("#'Purchase Entry'!A1", "📥 Purchase Entry") -> 📥 Purchase Entry | L4: =HYPERLINK("#'Sales Entry'!A1", "📤 Sales Entry") -> 📤 Sales Entry | O4: =HYPERLINK("#'Supplier Management'!A1", "🤝 Suppliers") -> 🤝 Suppliers | R4: =HYPERLINK("#'Reports'!A1", "📈 Reports") -> 📈 Reports
A6: Sales ID | B6: Date | C6: Product ID | D6: Product Name | E6: Quantity Sold | F6: Selling Price | G6: Total Amount | H6: Payment Method
A7: ="SAL-" & TEXT(ROW()-6, "00000") -> SAL-00001 | B7: 46038 | C7: PRD-00001 | D7: =IF(C7="", "", VLOOKUP(C7, 'Product Master'!$A:$I, 2, FALSE)) -> Sony WH-1000XM4 Headphones | E7: 10 | F7: =IF(C7="", "", VLOOKUP(C7, 'Product Master'!$A:$I, 7, FALSE)) -> 250 | G7: =E7 * F7 -> 2500 | H7: Cash
A8: ="SAL-" & TEXT(ROW()-6, "00000") -> SAL-00002 | B8: 46044 | C8: PRD-00002 | D8: =IF(C8="", "", VLOOKUP(C8, 'Product Master'!$A:$I, 2, FALSE)) -> Samsung 27" Curved Monitor | E8: 1 | F8: =IF(C8="", "", VLOOKUP(C8, 'Product Master'!$A:$I, 7, FALSE)) -> 180 | G8: =E8 * F8 -> 180 | H8: Credit Card
A9: ="SAL-" & TEXT(ROW()-6, "00000") -> SAL-00003 | B9: 46047 | C9: PRD-00001 | D9: =IF(C9="", "", VLOOKUP(C9, 'Product Master'!$A:$I, 2, FALSE)) -> Sony WH-1000XM4 Headphones | E9: 1 | F9: =IF(C9="", "", VLOOKUP(C9, 'Product Master'!$A:$I, 7, FALSE)) -> 250 | G9: =E9 * F9 -> 250 | H9: Debit Card
A10: ="SAL-" & TEXT(ROW()-6, "00000") -> SAL-00004 | B10: 46059 | C10: PRD-00003 | D10: =IF(C10="", "", VLOOKUP(C10, 'Product Master'!$A:$I, 2, FALSE)) -> Apple iPad Air (64GB) | E10: 2 | F10: =IF(C10="", "", VLOOKUP(C10, 'Product Master'!$A:$I, 7, FALSE)) -> 549 | G10: =E10 * F10 -> 1098 | H10: Mobile Wallet
A11: ="SAL-" & TEXT(ROW()-6, "00000") -> SAL-00005 | B11: 46065 | C11: PRD-00006 | D11: =IF(C11="", "", VLOOKUP(C11, 'Product Master'!$A:$I, 2, FALSE)) -> SanDisk Extreme 128GB USB-C | E11: 3 | F11: =IF(C11="", "", VLOOKUP(C11, 'Product Master'!$A:$I, 7, FALSE)) -> 29.99 | G11: =E11 * F11 -> 89.97 | H11: Cash
A12: ="SAL-" & TEXT(ROW()-6, "00000") -> SAL-00006 | B12: 46067 | C12: PRD-00001 | D12: =IF(C12="", "", VLOOKUP(C12, 'Product Master'!$A:$I, 2, FALSE)) -> Sony WH-1000XM4 Headphones | E12: 4 | F12: =IF(C12="", "", VLOOKUP(C12, 'Product Master'!$A:$I, 7, FALSE)) -> 250 | G12: =E12 * F12 -> 1000 | H12: Credit Card
A13: ="SAL-" & TEXT(ROW()-6, "00000") -> SAL-00007 | B13: 46073 | C13: PRD-00002 | D13: =IF(C13="", "", VLOOKUP(C13, 'Product Master'!$A:$I, 2, FALSE)) -> Samsung 27" Curved Monitor | E13: 2 | F13: =IF(C13="", "", VLOOKUP(C13, 'Product Master'!$A:$I, 7, FALSE)) -> 180 | G13: =E13 * F13 -> 360 | H13: Debit Card
A14: ="SAL-" & TEXT(ROW()-6, "00000") -> SAL-00008 | B14: 46083 | C14: PRD-00011 | D14: =IF(C14="", "", VLOOKUP(C14, 'Product Master'!$A:$I, 2, FALSE)) -> Nike Air Max Sneakers | E14: 6 | F14: =IF(C14="", "", VLOOKUP(C14, 'Product Master'!$A:$I, 7, FALSE)) -> 120 | G14: =E14 * F14 -> 720 | H14: Bank Transfer
A15: ="SAL-" & TEXT(ROW()-6, "00000") -> SAL-00009 | B15: 46085 | C15: PRD-00015 | D15: =IF(C15="", "", VLOOKUP(C15, 'Product Master'!$A:$I, 2, FALSE)) -> H&M Basic Crewneck T-Shirt | E15: 10 | F15: =IF(C15="", "", VLOOKUP(C15, 'Product Master'!$A:$I, 7, FALSE)) -> 6 | G15: =E15 * F15 -> 60 | H15: Cash
A16: ="SAL-" & TEXT(ROW()-6, "00000") -> SAL-00010 | B16: 46089 | C16: PRD-00021 | D16: =IF(C16="", "", VLOOKUP(C16, 'Product Master'!$A:$I, 2, FALSE)) -> Nestlé Pure Life Water (24pk) | E16: 20 | F16: =IF(C16="", "", VLOOKUP(C16, 'Product Master'!$A:$I, 7, FALSE)) -> 0.21 | G16: =E16 * F16 -> 4.2 | H16: Mobile Wallet
A17: ="SAL-" & TEXT(ROW()-6, "00000") -> SAL-00011 | B17: 46093 | C17: PRD-00031 | D17: =IF(C17="", "", VLOOKUP(C17, 'Product Master'!$A:$I, 2, FALSE)) -> Pfizer Advil Pain Reliever (100ct) | E17: 12 | F17: =IF(C17="", "", VLOOKUP(C17, 'Product Master'!$A:$I, 7, FALSE)) -> 9.49 | G17: =E17 * F17 -> 113.88 | H17: Credit Card
A18: ="SAL-" & TEXT(ROW()-6, "00000") -> SAL-00012 | B18: 46099 | C18: PRD-00041 | D18: =IF(C18="", "", VLOOKUP(C18, 'Product Master'!$A:$I, 2, FALSE)) -> Dyson V11 Cordless Vacuum | E18: 2 | F18: =IF(C18="", "", VLOOKUP(C18, 'Product Master'!$A:$I, 7, FALSE)) -> 599.99 | G18: =E18 * F18 -> 1199.98 | H18: Bank Transfer
... A27: ="SAL-" & TEXT(ROW()-6, "00000") -> SAL-00021 | B27: 46160 | C27: PRD-00041 | D27: =IF(C27="", "", VLOOKUP(C27, 'Product Master'!$A:$I, 2, FALSE)) -> Dyson V11 Cordless Vacuum | E27: 10 | F27: =IF(C27="", "", VLOOKUP(C27, 'Product Master'!$A:$I, 7, FALSE)) -> 599.99 | G27: =E27 * F27 -> 5999.9 | H27: Bank Transfer

Sheet Supplier Management
A1: SUPPLIER DIRECTORY
A4: =HYPERLINK("#'Dashboard'!A1", "📊 Dashboard") -> 📊 Dashboard | D4: =HYPERLINK("#'Product Master'!A1", "📦 Product Master") -> 📦 Product Master | H4: =HYPERLINK("#'Purchase Entry'!A1", "📥 Purchase Entry") -> 📥 Purchase Entry | L4: =HYPERLINK("#'Sales Entry'!A1", "📤 Sales Entry") -> 📤 Sales Entry | O4: =HYPERLINK("#'Supplier Management'!A1", "🤝 Suppliers") -> 🤝 Suppliers | R4: =HYPERLINK("#'Reports'!A1", "📈 Reports") -> 📈 Reports
A6: Supplier ID | B6: Supplier Name | C6: Contact Person | D6: Phone | E6: Email | F6: Address
A7: SPL-0001 | B7: Apex Distributors | C7: John Smith | D7: 555-0101 | E7: sales@apex.com | F7: 123 Industrial Pkwy, New York, NY
A8: SPL-0002 | B8: Summit Wholesale | C8: Sarah Connor | D8: 555-0102 | E8: contact@summit.com | F8: 456 Commerce Blvd, Los Angeles, CA
A9: SPL-0003 | B9: Prime Logistics | C9: David Miller | D9: 555-0103 | E9: logistics@prime.com | F9: 789 Supply Rd, Chicago, IL
A10: SPL-0004 | B10: Global Trade Co. | C10: Elena Rostova | D10: 555-0104 | E10: trade@global.com | F10: 101 Port Way, Miami, FL
A11: SPL-0005 | B11: BioPharma Supplies | C11: Alan Grant | D11: 555-0105 | E11: supplies@biopharma.com | F11: 202 Lab Circle, Boston, MA

Sheet ReferenceLists
A1: Categories | B1: Locations | C1: Payment Methods
A2: Electronics | B2: Aisle A | C2: Cash
A3: Apparel | B3: Aisle B | C3: Credit Card
A4: Grocery | B4: Aisle C | C4: Debit Card
A5: Pharmacy | B5: Aisle D | C5: Mobile Wallet
A6: Home & Kitchen | B6: Warehouse | C6: Bank Transfer
